<?xml version="1.0"?>
<opencv_storage>
<stage14>
  <maxWeakCount>10</maxWeakCount>
  <stageThreshold>-2.0252313613891602e+00</stageThreshold>
  <weakClassifiers>
    <_>
      <internalNodes>
        0 -1 19151 -538069729 -201911809 287536127 -605301257
        -1011770881 -70581829 -1145332737 -8390021</internalNodes>
      <leafValues>
        -8.7042003870010376e-01 -6.9090910255908966e-02</leafValues></_>
    <_>
      <internalNodes>
        0 -1 29172 -562832641 -320989203 -1180968481 -170455555
        724728282 -295763553 2140783519 -543188353</internalNodes>
      <leafValues>
        -5.8252567052841187e-01 2.0911797881126404e-01</leafValues></_>
    <_>
      <internalNodes>
        0 -1 24531 -1143876408 -1789163204 84484095 1535087199 -79238198
        -579356018 -1644242995 -1748249057</internalNodes>
      <leafValues>
        -3.7440386414527893e-01 3.9754125475883484e-01</leafValues></_>
    <_>
      <internalNodes>
        0 -1 26405 -1325705498 1128584295 -124863236 -37233849
        1502164518 20915591 -1337174235 -1340639273</internalNodes>
      <leafValues>
        -6.7555755376815796e-01 2.1743080019950867e-01</leafValues></_>
    <_>
      <internalNodes>
        0 -1 14244 939448531 1935060781 1942484959 -243339653
        -1007245841 -402665505 -1579182849 -955056742</internalNodes>
      <leafValues>
        -3.1291702389717102e-01 5.0915259122848511e-01</leafValues></_>
    <_>
      <internalNodes>
        0 -1 17193 -90774882 2114767514 1367791871 2055019484
        -1433223305 -470838930 2053348204 -1995517878</internalNodes>
      <leafValues>
        -4.7822618484497070e-01 3.2579708099365234e-01</leafValues></_>
    <_>
      <internalNodes>
        0 -1 6804 -1730872436 1913313776 -661850485 -441400572
        1762282733 285938369 596359694 1092571743</internalNodes>
      <leafValues>
        -5.3972113132476807e-01 2.8115397691726685e-01</leafValues></_>
    <_>
      <internalNodes>
        0 -1 20883 1669818791 1321660772 1011439094 1318046633 151567205
        2024048884 534477360 1293478111</internalNodes>
      <leafValues>
        -7.6017385721206665e-01 1.8621224164962769e-01</leafValues></_>
    <_>
      <internalNodes>
        0 -1 30810 -277385919 -154173829 -1437372425 -741900419
        -1268844568 -729024640 914081755 -1725958657</internalNodes>
      <leafValues>
        -3.2405352592468262e-01 5.0456720590591431e-01</leafValues></_>
    <_>
      <internalNodes>
        0 -1 26720 1839089276 -3189797 957567811 853476315 -1027030550
        -1607598056 -1719287553 -1081436999</internalNodes>
      <leafValues>
        -4.1743838787078857e-01 4.0695884823799133e-01</leafValues></_></weakClassifiers></stage14>
</opencv_storage>
